compteurvues/__init__.py
compteurvues/admin.py
compteurvues/apps.py
compteurvues/models.py
compteurvues/urls.py
compteurvues/views.py
compteurvues/migrations/0001_initial.py
compteurvues/migrations/__init__.py
compteurvues/templates/compteurvues/compteur.html
django_compteurvues-0.1.0.dist-info/METADATA
django_compteurvues-0.1.0.dist-info/WHEEL
django_compteurvues-0.1.0.dist-info/top_level.txt
django_compteurvues-0.1.0.dist-info/RECORD
